MANIFEST.in
README
VERSION
setup.cfg
setup.py
docs/default.cfg.sample
docs/license.txt
docs/release.howto
feed2twitter/__init__.py
feed2twitter/options.py
feed2twitter/parsetime.py
feed2twitter/readrss.py
feed2twitter/shortener.py
feed2twitter.egg-info/PKG-INFO
feed2twitter.egg-info/SOURCES.txt
feed2twitter.egg-info/dependency_links.txt
feed2twitter.egg-info/entry_points.txt
feed2twitter.egg-info/not-zip-safe
feed2twitter.egg-info/top_level.txt
scripts/feed2twitter