Metadata-Version: 1.0
Name: feed2twitter
Version: 0.6.5
Summary: Publish your feed items to twitter
Home-page: http://www.assembla.com/spaces/feed2twitter
Author: Walter Cruz
Author-email: walter@waltercruz.com
License: AGPL
Keywords: twitter feed
Platform: UNKNOWN
Classifier: Intended Audience :: Developers
Classifier: Programming Language :: Python
Classifier: Environment :: Console
Classifier: Development Status :: 3 - Alpha
